sopel_joinall/__init__.py
sopel_joinall/joinall/__init__.py
sopel_plugins.joinall-1.0.4.dist-info/LICENSE
sopel_plugins.joinall-1.0.4.dist-info/METADATA
sopel_plugins.joinall-1.0.4.dist-info/WHEEL
sopel_plugins.joinall-1.0.4.dist-info/entry_points.txt
sopel_plugins.joinall-1.0.4.dist-info/top_level.txt
sopel_plugins.joinall-1.0.4.dist-info/RECORD
