Metadata-Version: 2.1
Name: sopel-plugins.joinall
Version: 1.0.4
Summary: joinall plugin for Sopel
Home-page: https://github.com/MirahezeBots/sopel-joinall
Author: MirahezeBot Contributors
Author-email: staff@mirahezebots.org
License: Eiffel Forum License, version 2
Platform: UNKNOWN
Classifier: Development Status :: 5 - Production/Stable
Classifier: Intended Audience :: Developers
Classifier: Intended Audience :: System Administrators
Classifier: License :: Eiffel Forum License (EFL)
Classifier: License :: OSI Approved :: Eiffel Forum License
Classifier: Operating System :: POSIX :: Linux
Classifier: Operating System :: Microsoft :: Windows
Classifier: Operating System :: MacOS
Classifier: Programming Language :: Python :: 3.6
Classifier: Programming Language :: Python :: 3.7
Classifier: Programming Language :: Python :: 3.8
Classifier: Programming Language :: Python :: 3.9
Classifier: Topic :: Communications :: Chat :: Internet Relay Chat
Requires-Python: >=3.6
License-File: LICENSE
Requires-Dist: sopel (<8,>=7.1.1)
Requires-Dist: wheel (<0.37.0,>=0.36.2)
